textmode/__init__.py
textmode/server.py
textmode/engine/__init__.py
textmode/engine/console.py
textmode/roms/_2048.py
textmode/roms/__init__.py
textmode/roms/demo.py
textmode/roms/menu.py
textmode/roms/rogue.py
textmode/roms/tetris.py
textmode/roms/trivia.py
textmode/www/index.html
textmode/www/inspect.html
textmode/www/font/dungeon-mode-inverted.ttf
textmode/www/font/dungeon-mode.ttf
textmode-0.3.0.dist-info/METADATA
textmode-0.3.0.dist-info/WHEEL
textmode-0.3.0.dist-info/RECORD
